fileconvtools/__init__.py
fileconvtools/main.py
fileconvtools/temp.py
fileconvtools-0.0.4.dist-info/LICENSE
fileconvtools-0.0.4.dist-info/METADATA
fileconvtools-0.0.4.dist-info/WHEEL
fileconvtools-0.0.4.dist-info/top_level.txt
fileconvtools-0.0.4.dist-info/RECORD
